README.rst
setup.py
ffnetui/__init__.py
ffnetui/about.py
ffnetui/actions.py
ffnetui/animations.py
ffnetui/data.py
ffnetui/dumper.py
ffnetui/ffnetapp.py
ffnetui/ffnetui.py
ffnetui/graph_layout.py
ffnetui/loadtxt.py
ffnetui/logger.py
ffnetui/messages.py
ffnetui/network.py
ffnetui/process.py
ffnetui/progress.py
ffnetui/redirfile.py
ffnetui/shared.py
ffnetui/training.py
ffnetui/version.py
ffnetui.egg-info/PKG-INFO
ffnetui.egg-info/SOURCES.txt
ffnetui.egg-info/dependency_links.txt
ffnetui.egg-info/entry_points.txt
ffnetui.egg-info/requires.txt
ffnetui.egg-info/top_level.txt
ffnetui/data/black-scholes-input.dat
ffnetui/data/black-scholes-target.dat
ffnetui/data/black-scholes.dat
ffnetui/data/cite.txt
ffnetui/data/eps-sigma-input.txt
ffnetui/data/eps-sigma-target.txt
ffnetui/data/testnet.net
ffnetui/images/accessories-text-editor.png
ffnetui/images/document-new.png
ffnetui/images/document-open.png
ffnetui/images/document-save-as.png
ffnetui/images/edit-clear.png
ffnetui/images/face-smile.png
ffnetui/images/ffnetui128x128.ico
ffnetui/images/ffnetui128x128.png
ffnetui/images/ffnetui22x22.ico
ffnetui/images/ffnetui256x256.png
ffnetui/images/ffnetui600x600.png
ffnetui/images/go-next.png
ffnetui/images/help-browser.png
ffnetui/images/matplotlib.png
ffnetui/images/media-record.png
ffnetui/images/preferences-system.png
ffnetui/images/process-stop.png
ffnetui/images/text-x-fortran.png
ffnetui/images/text-x-generic-template.png
ffnetui/images/text-x-generic.png
ffnetui/images/text-x-ok.png
ffnetui/images/user-trash.png
ffnetui/plots/__init__.py
ffnetui/plots/mplconfig.py
ffnetui/plots/mplfigure.py
ffnetui/plots/mplqt.py
ffnetui/plots/mpltools.py
ffnetui/plots/mplwx.py
ffnetui/plots/images/preferences-system-mpl.png