Metadata-Version: 1.1
Name: ffnetui
Version: 0.8.3.2
Summary: GUI for ffnet - feed-forward neural network for python
Home-page: http://ffnet.sourceforge.net
Author: Marek Wojciechowski
Author-email: mwojc@p.lodz.pl
License: GPL-3
Platform: Posix
Platform: Windows
Classifier: Development Status :: 4 - Beta
Classifier: Environment :: Win32 (MS Windows)
Classifier: Environment :: X11 Applications
Classifier: Intended Audience :: Education
Classifier: Intended Audience :: End Users/Desktop
Classifier: Intended Audience :: Science/Research
Classifier: License :: OSI Approved :: GNU General Public License v3 (GPLv3)
Classifier: Operating System :: OS Independent
Classifier: Programming Language :: Python :: 2.7
Classifier: Topic :: Scientific/Engineering :: Artificial Intelligence
Requires: ffnet
Requires: traitsui
Requires: matplotlib
